expressify/__init__.py
expressify/lib/__init__.py
expressify/lib/application.py
expressify/lib/middleware.py
expressify/lib/request.py
expressify/lib/response.py
expressify/lib/router.py
expressify/lib/template.py
expressify-0.1.0.dist-info/licenses/LICENSE
expressify-0.1.0.dist-info/METADATA
expressify-0.1.0.dist-info/WHEEL
expressify-0.1.0.dist-info/top_level.txt
expressify-0.1.0.dist-info/RECORD
