Metadata-Version: 2.4
Name: expressify
Version: 0.1.0
Summary: A lightweight Express.js-inspired web framework for Python
Home-page: https://github.com/itsdhruvrawat/expressify
Author: Dhruv Rawat
Author-email: dhruvrwt12@gmail.com
Project-URL: Bug Tracker, https://github.com/itsdhruvrawat/expressify/issues
Project-URL: Documentation, https://express-ify.netlify.app
Project-URL: Source Code, https://github.com/itsdhruvrawat/expressify
Keywords: web framework,express,http,api,routing,middleware
Classifier: Development Status :: 3 - Alpha
Classifier: Intended Audience :: Developers
Classifier: License :: OSI Approved :: MIT License
Classifier: Programming Language :: Python :: 3
Classifier: Programming Language :: Python :: 3.7
Classifier: Programming Language :: Python :: 3.8
Classifier: Programming Language :: Python :: 3.9
Classifier: Programming Language :: Python :: 3.10
Classifier: Programming Language :: Python :: 3.11
Classifier: Topic :: Internet :: WWW/HTTP :: HTTP Servers
Classifier: Topic :: Internet :: WWW/HTTP :: WSGI :: Application
Classifier: Topic :: Software Development :: Libraries :: Application Frameworks
Classifier: Operating System :: OS Independent
Requires-Python: >=3.7
License-File: LICENSE
Requires-Dist: jinja2>=2.11.0
Requires-Dist: uvicorn>=0.15.0
Provides-Extra: dev
Requires-Dist: pytest>=6.0.0; extra == "dev"
Requires-Dist: black>=21.5b2; extra == "dev"
Requires-Dist: flake8>=3.9.2; extra == "dev"
Requires-Dist: isort>=5.9.1; extra == "dev"
Dynamic: author
Dynamic: author-email
Dynamic: classifier
Dynamic: description
Dynamic: description-content-type
Dynamic: home-page
Dynamic: keywords
Dynamic: license-file
Dynamic: project-url
Dynamic: provides-extra
Dynamic: requires-dist
Dynamic: requires-python
Dynamic: summary
